{"cameraMode":{"drawMode":0,"name":"Shaded","section":"Shading Mode"},"sceneLighting":false,"audioPlay":false,"sceneViewState":{"m_AlwaysRefresh":false,"showFog":true,"showSkybox":false,"showFlares":true,"showImageEffects":true,"showParticleSystems":true,"showVisualEffectGraphs":true,"m_FxEnabled":true},"in2DMode":false,"pivot":{"x":-3.111799478530884,"y":1.905616283416748,"z":-4.363282680511475},"rotation":{"x":0.17666539549827577,"y":0.34211310744285586,"z":-0.0656658485531807,"w":0.9206113219261169},"size":6.286251544952393,"orthographic":true}